owasp_dependency_track_azure_devops-0.0.2.dist-info/licenses/LICENSE
owasp_dt_sync/args.py
owasp_dt_sync/azure_helper.py
owasp_dt_sync/cli.py
owasp_dt_sync/config.py
owasp_dt_sync/globals.py
owasp_dt_sync/jinja.py
owasp_dt_sync/log.py
owasp_dt_sync/mappers.py
owasp_dt_sync/models.py
owasp_dt_sync/owasp_dt_helper.py
owasp_dt_sync/sync.py
owasp_dependency_track_azure_devops-0.0.2.dist-info/METADATA
owasp_dependency_track_azure_devops-0.0.2.dist-info/WHEEL
owasp_dependency_track_azure_devops-0.0.2.dist-info/entry_points.txt
owasp_dependency_track_azure_devops-0.0.2.dist-info/top_level.txt
owasp_dependency_track_azure_devops-0.0.2.dist-info/RECORD
