Metadata-Version: 2.4
Name: owasp-dependency-track-azure-devops
Version: 0.0.2
Summary: OWASP Dependency Track Azure DevOps sync
Requires-Python: >=3.13
License-File: LICENSE
Requires-Dist: owasp-dependency-track-client==4.13.6
Requires-Dist: is_empty==1.0.1
Requires-Dist: tinystream==0.1.18
Requires-Dist: dotenv==0.9.9
Requires-Dist: jinja2==3.1.6
Requires-Dist: azure-devops==7.1.0b4
Provides-Extra: build
Requires-Dist: build; extra == "build"
Requires-Dist: twine; extra == "build"
Provides-Extra: test
Requires-Dist: pytest>=7; extra == "test"
Dynamic: license-file
